mcp_sharepoint/__init__.py
mcp_sharepoint/common.py
mcp_sharepoint/exceptions.py
mcp_sharepoint/resources.py
mcp_sharepoint/server.py
mcp_sharepoint/settings.py
mcp_sharepoint/setup.py
mcp_sharepoint/tools.py
mcp_sharepoint_cert-0.3.0.dist-info/METADATA
mcp_sharepoint_cert-0.3.0.dist-info/WHEEL
mcp_sharepoint_cert-0.3.0.dist-info/entry_points.txt
mcp_sharepoint_cert-0.3.0.dist-info/licenses/LICENSE
mcp_sharepoint_cert-0.3.0.dist-info/RECORD
