Metadata-Version: 2.4
Name: mcp-sharepoint-cert
Version: 0.3.0
Summary: MCP Server to integrate with SharePoint
Project-URL: Homepage, https://github.com/peacockery-studio/mcp-sharepoint-cert
Project-URL: Repository, https://github.com/peacockery-studio/mcp-sharepoint-cert
Project-URL: Issues, https://github.com/peacockery-studio/mcp-sharepoint-cert/issues
Author-email: Chi Ejimofor <chi@peacockery.studio>
License-Expression: MIT
License-File: LICENSE
Requires-Python: >=3.12
Requires-Dist: mcp>=1.2.1
Requires-Dist: office365-rest-python-client>=2.6.1
Requires-Dist: openpyxl>=3.1.0
Requires-Dist: pandas>=2.0.0
Requires-Dist: pydantic-settings>=2.0.0
Requires-Dist: pydantic>=2.0.0
Requires-Dist: pymupdf>=1.23.0
Requires-Dist: python-docx>=1.1.0
Requires-Dist: python-dotenv>=1.0.0
Requires-Dist: rich>=13.0.0
Requires-Dist: typer>=0.15.0
